mcp_solver/__init__.py
mcp_solver/constants.py
mcp_solver/memo.py
mcp_solver/model_manager.py
mcp_solver/server.py
mcp_solver-2.0.0.dist-info/METADATA
mcp_solver-2.0.0.dist-info/WHEEL
mcp_solver-2.0.0.dist-info/entry_points.txt
mcp_solver-2.0.0.dist-info/licenses/LICENSE
mcp_solver-2.0.0.dist-info/RECORD
